cohash.py
cohash-0.1.4.dist-info/DESCRIPTION.rst
cohash-0.1.4.dist-info/METADATA
cohash-0.1.4.dist-info/metadata.json
cohash-0.1.4.dist-info/RECORD
cohash-0.1.4.dist-info/top_level.txt
cohash-0.1.4.dist-info/WHEEL
