Metadata-Version: 2.0
Name: cohash
Version: 0.1.4
Summary: Consistency hash algorithm implementation in Python.
Home-page: https://github.com/theharveyz/cohash.py
Author: harveyz
Author-email: zharvey@163.com
License: MIT
Platform: UNKNOWN
